README.rst
setup.py
Flask_RestClient.egg-info/PKG-INFO
Flask_RestClient.egg-info/SOURCES.txt
Flask_RestClient.egg-info/dependency_links.txt
Flask_RestClient.egg-info/requires.txt
Flask_RestClient.egg-info/top_level.txt
flask_rest_client/__init__.py