Metadata-Version: 1.1
Name: Flask-RestClient
Version: 0.1.1
Summary: restful api client for flask extension
Home-page: UNKNOWN
Author: codeif
Author-email: me@codeif.com
License: MIT
Platform: UNKNOWN
Classifier: Programming Language :: Python :: 3
